heptapp/__init__.py
heptapp-0.0.1.dist-info/LICENSE
heptapp-0.0.1.dist-info/METADATA
heptapp-0.0.1.dist-info/WHEEL
heptapp-0.0.1.dist-info/top_level.txt
heptapp-0.0.1.dist-info/RECORD
