Metadata-Version: 2.1
Name: heptapp
Version: 0.0.1
Summary: A bolierplate for heptagon applications
Author-email: Juan Cerezo <juancerezo.pro@gmail.com>
Classifier: Programming Language :: Python :: 3
Requires-Python: >=3.10
License-File: LICENSE
